sqlalchemybulk/__init__.py
sqlalchemybulk/crud.py
sqlalchemybulk/crud_helper_funcs.py
sqlalchemybulk/helper_functions.py
sqlalchemybulk/init_or_update_db.py
sqlalchemybulk/manager.py
sqlalchemybulk-0.1.4.dist-info/LICENSE
sqlalchemybulk-0.1.4.dist-info/METADATA
sqlalchemybulk-0.1.4.dist-info/WHEEL
sqlalchemybulk-0.1.4.dist-info/top_level.txt
sqlalchemybulk-0.1.4.dist-info/RECORD
