Metadata-Version: 2.1
Name: sqlalchemybulk
Version: 0.1.4
Summary: Perform CRUD operations with SQLAlchemy
Author-email: sudonorm <sudonorm@protonmail.com>
License: MIT License
Project-URL: repository, https://github.com/sudonorm/sqlalchemy-bulk
Keywords: database,sqlalchemy,upsert,bulk,orm,crud
Classifier: Development Status :: 5 - Production/Stable
Classifier: License :: OSI Approved :: MIT License
Classifier: Operating System :: OS Independent
Classifier: Programming Language :: Python
Classifier: Programming Language :: Python :: 3
Classifier: Programming Language :: Python :: 3.8
Classifier: Programming Language :: Python :: 3.9
Classifier: Programming Language :: Python :: 3.10
Classifier: Programming Language :: Python :: 3.11
Classifier: Programming Language :: Python :: 3.12
Classifier: Programming Language :: Python :: Implementation :: CPython
Classifier: Programming Language :: Python :: Implementation :: PyPy
Classifier: Topic :: Database :: Front-Ends
Requires-Python: >=3.7
License-File: LICENSE
Requires-Dist: SQLAlchemy>2.0.0
Requires-Dist: alembic>1.9.0
Requires-Dist: pandas>2.0.0
Requires-Dist: numpy
Requires-Dist: packaging
Requires-Dist: python-dotenv
Provides-Extra: build
Requires-Dist: build; extra == "build"
Requires-Dist: twine; extra == "build"
Provides-Extra: dev
Requires-Dist: black; extra == "dev"
Requires-Dist: bumpver; extra == "dev"
Requires-Dist: isort; extra == "dev"
Requires-Dist: mypy; extra == "dev"
Requires-Dist: pytest; extra == "dev"
